{
  "openapi": "3.0.1",
  "info": {
    "title": "My API",
    "version": "v1"
  },
  "paths": {
    "/WeatherForecast": {
      "get": {
        "tags": [
          "WeatherForecast"
        ],
        "parameters": [
          {
            "name": "value",
            "in": "query",
            "required": true,
            "schema": {
              "maximum": 5,
              "minimum": 1,
              "type": "integer",
              "format": "int32"
            }
          }
        ],
        "responses": {
          "200": {
            "description": "OK"
          }
        }
      }
    }
  }
}